MSG_Nbody/MSG_Nbody.py
MSG_Nbody/__init__.py
MSG_Nbody/acceleration_potential.py
MSG_Nbody/analysis.py
MSG_Nbody/input_output.py
MSG_Nbody/simulation_setup.py
msg_nbody-0.2.7.dist-info/LICENSE
msg_nbody-0.2.7.dist-info/METADATA
msg_nbody-0.2.7.dist-info/WHEEL
msg_nbody-0.2.7.dist-info/top_level.txt
msg_nbody-0.2.7.dist-info/RECORD
