Metadata-Version: 2.2
Name: MSG_Nbody
Version: 0.2.7
Summary: Nbody simulation code for galaxy interactions
Home-page: https://github.com/elkogerville/MSG_Nbody
Author: Elko Gerville-Reache
Author-email: Elko Gerville-Reache <elkogerville@gmail.com>
License: MIT
Classifier: Programming Language :: Python :: 3
Classifier: License :: OSI Approved :: MIT License
Classifier: Operating System :: OS Independent
Requires-Python: >=3.6
License-File: LICENSE
Requires-Dist: numpy
Requires-Dist: numba
Requires-Dist: tqdm
Requires-Dist: matplotlib
Requires-Dist: scipy
Dynamic: author
Dynamic: home-page
Dynamic: requires-python
